nonebot_plugin_manageweb/__init__.py
nonebot_plugin_manageweb/config.py
nonebot_plugin_manageweb/logger.py
nonebot_plugin_manageweb/plugins/models.py
nonebot_plugin_manageweb/plugins/utils.py
nonebot_plugin_manageweb/utils.py
nonebot_plugin_manageweb/web/api/__init__.py
nonebot_plugin_manageweb/web/api/env.py
nonebot_plugin_manageweb/web/api/home.py
nonebot_plugin_manageweb/web/api/plugin.py
nonebot_plugin_manageweb/web/page/__init__.py
nonebot_plugin_manageweb/web/page/env.py
nonebot_plugin_manageweb/web/page/home.py
nonebot_plugin_manageweb/web/page/login.py
nonebot_plugin_manageweb/web/page/main.py
nonebot_plugin_manageweb/web/page/plugin.py
nonebot_plugin_manageweb-0.1.6.dist-info/LICENSE
nonebot_plugin_manageweb-0.1.6.dist-info/METADATA
nonebot_plugin_manageweb-0.1.6.dist-info/WHEEL
nonebot_plugin_manageweb-0.1.6.dist-info/RECORD
