Metadata-Version: 2.3
Name: nonebot-plugin-manageweb
Version: 0.1.6
Summary: Nonebot插件商店安装插件，使用基于fastapi和amis的webui安装
Author: CM-Edelweiss
Author-email: 2633668472@qq.com
Requires-Python: >=3.10,<4.0
Classifier: Programming Language :: Python :: 3
Classifier: Programming Language :: Python :: 3.10
Classifier: Programming Language :: Python :: 3.11
Classifier: Programming Language :: Python :: 3.12
Classifier: Programming Language :: Python :: 3.13
Requires-Dist: amis-py-model (>=1.0.0,<2.0.0)
Requires-Dist: fastapi (>=0.93.0)
Requires-Dist: httpx (>=0.23.0,<0.24.0)
Requires-Dist: importlib-metadata (>=4.13.0)
Requires-Dist: nonebot2 (>=2.2.0,<3.0.0)
Requires-Dist: python-jose (>=3.3.0,<4.0.0)
Requires-Dist: toml (>=0.10.2)
